19-mult-punto-flotante/19-mult-punto-flotante/Fuentes/mult_flotante_pkg_tb.vhd
library IEEE;
	use IEEE.std_logic_1164.all;
	use IEEE.numeric_std.all;
	-- Paquete con funciones de conversión. Para poder utilizarlo en las simulaciones es
	-- necesario pasar el argumento "--std=08" a GHDL
	use IEEE.float_pkg.all;

	use work.tipo_punto_flotante_pkg.all;
	use work.mult_flotante_pkg.all;

entity mult_flotante_pkg_tb is
end entity;

architecture mult_flotante_pkg_tb_arq of mult_flotante_pkg_tb is

	signal clk_tb      : std_logic := '0';
	signal rst_tb      : std_logic := '1';
	signal ena_tb      : std_logic := '1';
	signal flotante1   : std_logic_vector(msb_completo downto 0);
	signal flotante2   : std_logic_vector(msb_completo downto 0);
	signal f1, f2, f3  : float32;
	signal resultado32 : std_logic_vector(msb_completo downto 0);
	signal sig         : std_logic;
	signal exp         : std_logic_vector(msb_exponente downto 0);
	signal man         : std_logic_vector(msb_mantisa downto 0);
	signal man_expandida: unsigned(tam_mantisa * 2 + 1 downto 0);

	signal instancia_mult_flot : registro_multiplicador_flotante;

begin

	clk_tb <= not clk_tb after 4 ns;
	rst_tb <= '0' after 140 ns, '1' after 520 ns;
	ena_tb <= '1' after 150 ns, '0' after 510 ns;
	f1     <= to_float(+ 25.15) after 150 ns, to_float(+ 1525.15) after 180 ns, to_float(- 105.15) after 210 ns, to_float(+ 0) after 240 ns;
	f2     <= to_float(+ 6.5) after 150 ns, to_float(+ 3.15) after 180 ns, to_float(+ 25.15) after 210 ns, to_float(+ 25.15) after 240 ns;
	-- La señal f3 se utiliza para comprobar que la salida se la misma que el multiplicador
	-- sintetizable.
	f3        <= f1 * f2;
	flotante1 <= to_std_logic_vector(f1);
	flotante2 <= to_std_logic_vector(f2);

	-- instancia_mult_flot <= ini_multiplicador_flotante;
	-- v1_punto_flotante   <= todos_ceros;
	-- v2_punto_flotante   <= todos_ceros;

	corrida: process (clk_tb)
		variable v1_punto_flotante : registro_flotante;
		variable v2_punto_flotante : registro_flotante;
	begin
		if (ena_tb) then
			--v1_punto_flotante.signo := flotante1(msb_completo);
			--v1_punto_flotante.exponente := signed(flotante1(msb_completo - 1 downto tam_mantisa));
			--v1_punto_flotante.mantisa := unsigned(flotante1(msb_mantisa downto 0));
			v1_punto_flotante := to_punto_flotante(flotante1);
			v2_punto_flotante := to_punto_flotante(flotante2);

			--v2_punto_flotante.signo := flotante2(msb_completo);
			--v2_punto_flotante.exponente := signed(flotante2(msb_completo - 1 downto tam_mantisa));
			--v2_punto_flotante.mantisa := unsigned(flotante2(msb_mantisa downto 0));

			if (rising_edge(clk_tb)) then
				if (rst_tb = '1') then
					resultado32 <= (others => '0');
				else
					crear_mult_flotante(instancia_mult_flot);

					request_float_multiplier(instancia_mult_flot, v1_punto_flotante, v2_punto_flotante);

					if float_multiplier_is_ready(instancia_mult_flot) then
						resultado32 <= get_multiplier_resultado(instancia_mult_flot);
						sig <= instancia_mult_flot.resultado.signo;
						exp <= std_logic_vector(instancia_mult_flot.resultado.exponente);
						man <= std_logic_vector(instancia_mult_flot.resultado.mantisa);
						man_expandida <= instancia_mult_flot.result_mult_mantisa;
					end if;
				end if;
			end if;
		end if;

	end process;

end architecture;

19-mult-punto-flotante/19-mult-punto-flotante/Simulacion/mult_flotante_pkg_tb.vcd
$date
  Mon Apr 29 13:03:11 2024
$end
$version
  GHDL v0
$end
$timescale
  1 fs
$end
$scope module standard $end
$upscope $end
$scope module textio $end
$upscope $end
$scope module std_logic_1164 $end
$upscope $end
$scope module numeric_std $end
$upscope $end
$scope module fixed_float_types $end
$upscope $end
$scope module math_real $end
$upscope $end
$scope module tipo_punto_flotante_pkg $end
$upscope $end
$scope module mult_flotante_pkg $end
$upscope $end
$scope module mult_flotante_pkg_tb $end
$var reg 1 ! clk_tb $end
$var reg 1 " rst_tb $end
$var reg 1 # ena_tb $end
$var reg 32 $ flotante1[31:0] $end
$var reg 32 % flotante2[31:0] $end
$var reg 32 & f1[8:-23] $end
$var reg 32 ' f2[8:-23] $end
$var reg 32 ( f3[8:-23] $end
$var reg 32 ) resultado32[31:0] $end
$var reg 1 * sig $end
$var reg 8 + exp[7:0] $end
$var reg 23 , man[22:0] $end
$var reg 48 - man_expandida[47:0] $end
$comment instancia_mult_flot is not handled $end
$upscope $end
$enddefinitions $end
#0
0!
1"
1#
bUUUUUUUUUUUUUUUUUUUUUUUUUUUUUUUU $
bUUUUUUUUUUUUUUUUUUUUUUUUUUUUUUUU %
bUUUUUUUUUUUUUUUUUUUUUUUUUUUUUUUU &
bUUUUUUUUUUUUUUUUUUUUUUUUUUUUUUUU '
bXXXXXXXXXXXXXXXXXXXXXXXXXXXXXXXX (
bUUUUUUUUUUUUUUUUUUUUUUUUUUUUUUUU )
U*
bUUUUUUUU +
bUUUUUUUUUUUUUUUUUUUUUUU ,
bUUUUUUUUUUUUUUUUUUUUUUUUUUUUUUUUUUUUUUUUUUUUUUUU -
#4000000
1!
b00000000000000000000000000000000 )
#8000000
0!
#12000000
1!
#16000000
0!
#20000000
1!
#24000000
0!
#28000000
1!
#32000000
0!
#36000000
1!
#40000000
0!
#44000000
1!
#48000000
0!
#52000000
1!
#56000000
0!
#60000000
1!
#64000000
0!
#68000000
1!
#72000000
0!
#76000000
1!
#80000000
0!
#84000000
1!
#88000000
0!
#92000000
1!
#96000000
0!
#100000000
1!
#104000000
0!
#108000000
1!
#112000000
0!
#116000000
1!
#120000000
0!
#124000000
1!
#128000000
0!
#132000000
1!
#136000000
0!
#140000000
1!
0"
#144000000
0!
#148000000
1!
#150000000
b01000001110010010011001100110011 $
b01000000110100000000000000000000 %
b01000001110010010011001100110011 &
b01000000110100000000000000000000 '
b01000011001000110111100110011001 (
#152000000
0!
#156000000
1!
#160000000
0!
#164000000
1!
bUXXXXXXXXXXXXXXXXXXXXXXXXXXXXXXX )
bXXXXXXXX +
bXXXXXXXXXXXXXXXXXXXXXXX ,
bXXXXXXXXXXXXXXXXXXXXXXXXXXXXXXXXXXXXXXXXXXXXXXXX -
#168000000
0!
#172000000
1!
b101000110111100110011001011100000000000000000000 -
#176000000
0!
#180000000
1!
b01000100101111101010010011001101 $
b01000000010010011001100110011010 %
b01000100101111101010010011001101 &
b01000000010010011001100110011010 '
b01000101100101100010000111001000 (
b01000011001000110111100110011001 )
0*
b10000110 +
b01000110111100110011001 ,
#184000000
0!
#188000000
1!
#192000000
0!
#196000000
1!
#200000000
0!
#204000000
1!
b100101100010000111001000001000101010100001010010 -
#208000000
0!
#210000000
b11000010110100100100110011001101 $
b01000001110010010011001100110011 %
b11000010110100100100110011001101 &
b01000001110010010011001100110011 '
b11000101001001010100100001011100 (
#212000000
1!
b01000101100101100010000111001000 )
b10001011 +
b00101100010000111001000 ,
#216000000
0!
#220000000
1!
#224000000
0!
#228000000
1!
b101001010100100001011100001001110010001111010111 -
#232000000
0!
#236000000
1!
b11000101001001010100100001011100 )
1*
b10001010 +
b01001010100100001011100 ,
#240000000
0!
b00000000000000000000000000000000 $
b00000000000000000000000000000000 &
b00000000000000000000000000000000 (
#244000000
1!
#248000000
0!
#252000000
1!
#256000000
0!
#260000000
1!
b011001001001100110011001100000000000000000000000 -
#264000000
0!
#268000000
1!
b00000010010010010011001100110011 )
0*
b00000100 +
b10010010011001100110011 ,
