19-mult-punto-flotante/19-mult-punto-flotante/Fuentes/mult_flotante_top.vhd
library IEEE;
	use IEEE.std_logic_1164.all;
	use IEEE.numeric_std.all;

	use work.tipo_punto_flotante_pkg.all;
	use work.mult_flotante_pkg.all;

	-- 19. Trabajo Práctico Final: Multiplicador de Punto Flotante

entity mult_flotante_top is
	port (
		clk_i       : in  std_logic;
		rst_i       : in  std_logic;
		iniciar_i   : in  std_logic;
		op1_i       : in  std_logic_vector(msb_completo downto 0);
		op2_i       : in  std_logic_vector(msb_completo downto 0);
		resultado_o : out std_logic_vector(msb_completo downto 0);
		listo_o     : out std_logic
	);
end entity;

architecture mult_flotante_top_arq of mult_flotante_top is
	signal instancia_mult_flot : registro_multiplicador_flotante;
begin
	process (clk_i, rst_i, iniciar_i, op1_i, op2_i)
		-- Variables para valores de entradas
		-- Variables para valores de operaciones
		variable op1_flotante, op2_flotante : registro_flotante := todos_ceros;

	begin
		op1_flotante := to_punto_flotante(op1_i);
		op2_flotante := to_punto_flotante(op2_i);

		if (rising_edge(clk_i)) then
			if (rst_i = '1') then
				resultado_o <= (others => '0');
				listo_o <= '0';
			else
				if iniciar_i = '0' then
					listo_o <= '0';
				else

					crear_mult_flotante(instancia_mult_flot);

					request_float_multiplier(instancia_mult_flot, op1_flotante, op2_flotante);

					if float_multiplier_is_ready(instancia_mult_flot) then
						listo_o <= '1';
						resultado_o <= get_multiplier_resultado(instancia_mult_flot);
					else
						listo_o <= '0';
					end if;
				end if;
			end if;
		end if;
	end process;

end architecture;

19-mult-punto-flotante/Fuentes/mult_flotante_top_tb.vhd
library IEEE;
	use IEEE.std_logic_1164.all;
	use IEEE.numeric_std.all;
	-- Paquete con funciones de conversión. Para poder utilizarlo en las simulaciones es
	-- necesario pasar el argumento "--std=08" a GHDL
	use IEEE.float_pkg.all;

	use work.tipo_punto_flotante_pkg.all;

entity mult_flotante_top_tb is
end entity;

architecture mult_flotante_tb_arq of mult_flotante_top_tb is

	component mult_flotante_top is
		port (
			clk_i       : in  std_logic;
			rst_i       : in  std_logic;
			iniciar_i   : in  std_logic;
			op1_i       : in  std_logic_vector(msb_completo downto 0);
			op2_i       : in  std_logic_vector(msb_completo downto 0);
			resultado_o : out std_logic_vector(msb_completo downto 0);
			listo_o     : out std_logic
		);
	end component;

	signal clk_tb      : std_logic := '0';
	signal rst_tb      : std_logic := '1';
	signal ini_tb      : std_logic := '0';
	signal listo_tb    : std_logic;
	signal flotante1   : std_logic_vector(msb_completo downto 0);
	signal flotante2   : std_logic_vector(msb_completo downto 0);
	signal f1, f2, f3  : float32;
	signal resultado32 : std_logic_vector(msb_completo downto 0);

begin

	clk_tb <= not clk_tb after 4 ns;
	rst_tb <= '0' after 120 ns, '1' after 520 ns;
	ini_tb <= '1' after 150 ns,
	'0' after 200 ns, 
	'1' after 210 ns, 
	'0' after 250 ns, 
	'1' after 260 ns, 
	'0' after 300 ns,
	'1' after 310 ns;
	f1     <= to_float(+ 25.15) after 150 ns, 
	to_float(+ 1525.15) after 190 ns, 
	to_float(- 105.15) after 230 ns, to_float(+ 0.0) after 270 ns;
	f2     <= to_float(+ 6.5) after 150 ns, to_float(+ 3.15) after 190 ns, to_float(+ 25.15) after 230 ns, to_float(+ 25.15) after 270 ns;
	-- La señal f3 se utiliza para comprobar que la salida se la misma que el multiplicador
	-- sintetizable (DUT_orig.resultado_o).
	f3        <= f1 * f2;
	flotante1 <= to_std_logic_vector(f1);
	flotante2 <= to_std_logic_vector(f2);

	-- Declarar el DUT de esta manera evita tener que incluir los compoenentes manualmente
	DUT_orig: entity work.mult_flotante_top
		port map (
			clk_i       => clk_tb,
			rst_i       => rst_tb,
			iniciar_i   => ini_tb,
			op1_i       => flotante1,
			op2_i       => flotante2,
			resultado_o => resultado32,
			listo_o     => listo_tb

		);

end architecture;

19-mult-punto-flotante/19-mult-punto-flotante/Simulacion/mult_flotante_top_tb.vcd
$date
  Mon Apr 29 12:41:14 2024
$end
$version
  GHDL v0
$end
$timescale
  1 fs
$end
$scope module standard $end
$upscope $end
$scope module textio $end
$upscope $end
$scope module std_logic_1164 $end
$upscope $end
$scope module numeric_std $end
$upscope $end
$scope module fixed_float_types $end
$upscope $end
$scope module math_real $end
$upscope $end
$scope module tipo_punto_flotante_pkg $end
$upscope $end
$scope module mult_flotante_pkg $end
$upscope $end
$scope module mult_flotante_top_tb $end
$var reg 1 ! clk_tb $end
$var reg 1 " rst_tb $end
$var reg 1 # ini_tb $end
$var reg 1 $ listo_tb $end
$var reg 32 % flotante1[31:0] $end
$var reg 32 & flotante2[31:0] $end
$var reg 32 ' f1[8:-23] $end
$var reg 32 ( f2[8:-23] $end
$var reg 32 ) f3[8:-23] $end
$var reg 32 * resultado32[31:0] $end
$scope module dut_orig $end
$var reg 1 + clk_i $end
$var reg 1 , rst_i $end
$var reg 1 - iniciar_i $end
$var reg 32 . op1_i[31:0] $end
$var reg 32 / op2_i[31:0] $end
$var reg 32 0 resultado_o[31:0] $end
$var reg 1 1 listo_o $end
$comment instancia_mult_flot is not handled $end
$upscope $end
$upscope $end
$enddefinitions $end
#0
0!
1"
0#
U$
bUUUUUUUUUUUUUUUUUUUUUUUUUUUUUUUU %
bUUUUUUUUUUUUUUUUUUUUUUUUUUUUUUUU &
bUUUUUUUUUUUUUUUUUUUUUUUUUUUUUUUU '
bUUUUUUUUUUUUUUUUUUUUUUUUUUUUUUUU (
bXXXXXXXXXXXXXXXXXXXXXXXXXXXXXXXX )
bUUUUUUUUUUUUUUUUUUUUUUUUUUUUUUUU *
0+
1,
0-
bUUUUUUUUUUUUUUUUUUUUUUUUUUUUUUUU .
bUUUUUUUUUUUUUUUUUUUUUUUUUUUUUUUU /
bUUUUUUUUUUUUUUUUUUUUUUUUUUUUUUUU 0
U1
#4000000
1!
0$
b00000000000000000000000000000000 *
1+
b00000000000000000000000000000000 0
01
#8000000
0!
0+
#12000000
1!
1+
#16000000
0!
0+
#20000000
1!
1+
#24000000
0!
0+
#28000000
1!
1+
#32000000
0!
0+
#36000000
1!
1+
#40000000
0!
0+
#44000000
1!
1+
#48000000
0!
0+
#52000000
1!
1+
#56000000
0!
0+
#60000000
1!
1+
#64000000
0!
0+
#68000000
1!
1+
#72000000
0!
0+
#76000000
1!
1+
#80000000
0!
0+
#84000000
1!
1+
#88000000
0!
0+
#92000000
1!
1+
#96000000
0!
0+
#100000000
1!
1+
#104000000
0!
0+
#108000000
1!
1+
#112000000
0!
0+
#116000000
1!
1+
#120000000
0!
0"
0+
0,
#124000000
1!
1+
#128000000
0!
0+
#132000000
1!
1+
#136000000
0!
0+
#140000000
1!
1+
#144000000
0!
0+
#148000000
1!
1+
#150000000
1#
b01000001110010010011001100110011 %
b01000000110100000000000000000000 &
b01000001110010010011001100110011 '
b01000000110100000000000000000000 (
b01000011001000110111100110011001 )
1-
b01000001110010010011001100110011 .
b01000000110100000000000000000000 /
#152000000
0!
0+
#156000000
1!
1+
#160000000
0!
0+
#164000000
1!
1+
#168000000
0!
0+
#172000000
1!
1+
#176000000
0!
0+
#180000000
1!
1$
b01000011001000110111100110011001 *
1+
b01000011001000110111100110011001 0
11
#184000000
0!
0+
#188000000
1!
1+
#190000000
b01000100101111101010010011001101 %
b01000000010010011001100110011010 &
b01000100101111101010010011001101 '
b01000000010010011001100110011010 (
b01000101100101100010000111001000 )
b01000100101111101010010011001101 .
b01000000010010011001100110011010 /
#192000000
0!
0+
#196000000
1!
1+
#200000000
0!
0#
0+
0-
#204000000
1!
0$
1+
01
#208000000
0!
0+
#210000000
1#
1-
#212000000
1!
1$
1+
11
#216000000
0!
0+
#220000000
1!
1+
#224000000
0!
0+
#228000000
1!
b01000101100101100010000111001000 *
1+
b01000101100101100010000111001000 0
#230000000
b11000010110100100100110011001101 %
b01000001110010010011001100110011 &
b11000010110100100100110011001101 '
b01000001110010010011001100110011 (
b11000101001001010100100001011100 )
b11000010110100100100110011001101 .
b01000001110010010011001100110011 /
#232000000
0!
0+
#236000000
1!
1+
#240000000
0!
0+
#244000000
1!
1+
#248000000
0!
0+
#250000000
0#
0-
#252000000
1!
0$
1+
01
#256000000
0!
0+
#260000000
1!
1#
1$
1+
1-
11
#264000000
0!
0+
#268000000
1!
b11000101001001010100100001011100 *
1+
b11000101001001010100100001011100 0
#270000000
b00000000000000000000000000000000 %
b00000000000000000000000000000000 '
b00000000000000000000000000000000 )
b00000000000000000000000000000000 .
#272000000
0!
0+
#276000000
1!
1+
#280000000
0!
0+
#284000000
1!
1+
#288000000
0!
0+
#292000000
1!
1+
#296000000
0!
0+
#300000000
1!
0#
0$
1+
0-
01
#304000000
0!
0+
#308000000
1!
1+
#310000000
1#
1-
#312000000
0!
0+
#316000000
1!
1$
b00000010010010010011001100110011 *
1+
b00000010010010010011001100110011 0
11
